aeroval_parallelize/__init__.py
aeroval_parallelize/aeroval_parallelise.py
aeroval_parallelize/aeroval_run_json_cfg.py
pyaerocom_parallelization-0.0.5.dist-info/LICENSE
pyaerocom_parallelization-0.0.5.dist-info/METADATA
pyaerocom_parallelization-0.0.5.dist-info/WHEEL
pyaerocom_parallelization-0.0.5.dist-info/entry_points.txt
pyaerocom_parallelization-0.0.5.dist-info/top_level.txt
pyaerocom_parallelization-0.0.5.dist-info/RECORD
